[
    {
        "model": "main.habit",
        "pk": 1,
        "fields": {
            "owner": 1,
            "place_habit": "Место выполнения привычки 1",
            "time_habit": "12:30",
            "get_habit": "Что делаем (например, приседаем) 1",
            "nice_habit": true,
            "associated_habit": "Приятная связанная привычка 1",
            "period_habit": "Каждый день",
            "reward_habit": "Награда за выполнение привычки 1",
            "time_limit": 60,
            "is_public": true
        }
    },
    {
        "model": "main.habit",
        "pk": 2,
        "fields": {
            "owner": 1,
            "place_habit": "Место выполнения привычки 2",
            "time_habit": "12:30",
            "get_habit": "Что делаем (например, приседаем) 2",
            "nice_habit": false,
            "associated_habit": "Приятная связанная привычка 2",
            "period_habit": "Один раз в неделю",
            "reward_habit": "Награда за выполнение привычки 2",
            "time_limit": 45,
            "is_public": false
        }
    },
    {
        "model": "main.habit",
        "pk": 2,
        "fields": {
            "owner": 1,
            "place_habit": "Место выполнения привычки 3",
            "time_habit": "12:30",
            "get_habit": "Что делаем (например, приседаем) 3",
            "nice_habit": true,
            "associated_habit": "Приятная связанная привычка 3",
            "period_habit": "Два раза в неделю",
            "reward_habit": "Награда за выполнение привычки 3",
            "time_limit": 30,
            "is_public": true
        }
    },
    {
        "model": "main.habit",
        "pk": 2,
        "fields": {
            "owner": 1,
            "place_habit": "Место выполнения привычки 4",
            "time_habit": "12:30",
            "get_habit": "Что делаем (например, приседаем) 4",
            "nice_habit": false,
            "associated_habit": "Приятная связанная привычка 4",
            "period_habit": "Три раза в неделю",
            "reward_habit": "Награда за выполнение привычки 4",
            "time_limit": 90,
            "is_public": true
        }
    },
    {
        "model": "main.habit",
        "pk": 2,
        "fields": {
            "owner": 1,
            "place_habit": "Место выполнения привычки 5",
            "time_habit": "12:30",
            "get_habit": "Что делаем (например, приседаем) 5",
            "nice_habit": true,
            "associated_habit": "Приятная связанная привычка 5",
            "period_habit": "Четыре раза в неделю",
            "reward_habit": "Награда за выполнение привычки 5",
            "time_limit": 120,
            "is_public": false
        }
    },
    {
        "model": "main.habit",
        "pk": 1,
        "fields": {
            "owner": 1,
            "place_habit": "Место выполнения привычки 6",
            "time_habit": "12:30",
            "get_habit": "Что делаем (например, приседаем) 6",
            "nice_habit": false,
            "associated_habit": "Приятная связанная привычка 6",
            "period_habit": "Пять раз в неделю",
            "reward_habit": "Награда за выполнение привычки 6",
            "time_limit": 15,
            "is_public": true
        }
    },
    {
        "model": "main.habit",
        "pk": 1,
        "fields": {
            "owner": 1,
            "place_habit": "Место выполнения привычки 7",
            "time_habit": "12:30",
            "get_habit": "Что делаем (например, приседаем) 7",
            "nice_habit": true,
            "associated_habit": "Приятная связанная привычка 7",
            "period_habit": "Шесть раз в неделю",
            "reward_habit": "Награда за выполнение привычки 7",
            "time_limit": 75,
            "is_public": false
        }
    },
    {
        "model": "main.habit",
        "pk": 1,
        "fields": {
            "owner": 1,
            "place_habit": "Место выполнения привычки 8",
            "time_habit": "12:30",
            "get_habit": "Что делаем (например, приседаем) 8",
            "nice_habit": false,
            "associated_habit": "Приятная связанная привычка 8",
            "period_habit": "Каждый день",
            "reward_habit": "Награда за выполнение привычки 8",
            "time_limit": 105,
            "is_public": true
        }
    },
    {
        "model": "main.habit",
        "pk": 1,
        "fields": {
            "owner": 1,
            "place_habit": "Место выполнения привычки 9",
            "time_habit": "12:30",
            "get_habit": "Что делаем (например, приседаем) 9",
            "nice_habit": true,
            "associated_habit": "Приятная связанная привычка 9",
            "period_habit": "Один раз в неделю",
            "reward_habit": "Награда за выполнение привычки 9",
            "time_limit": 30,
            "is_public": true
        }
    },
    {
        "model": "main.habit",
        "pk": 1,
        "fields": {
            "owner": 1,
            "place_habit": "Место выполнения привычки 10",
            "time_habit": "12:30",
            "get_habit": "Что делаем (например, приседаем) 10",
            "nice_habit": false,
            "associated_habit": "Приятная связанная привычка 10",
            "period_habit": "Два раза в неделю",
            "reward_habit": "Награда за выполнение привычки 10",
            "time_limit": 90,
            "is_public": false
        }
    }
]
